Full_adder.v
module Full_adder (
    output Cout, Sum,
    input A, B, Cin
);
    assign Cout = (A & B) | (B & Cin) | (A & Cin);
    assign Sum = A ^ B ^ Cin;
endmodule

Adder32.v
module Adder32 (
    output Cout, 
    output [31:0] Sum,
    input [31:0] A, B,
    input Cin
);
    wire [31:1] ctemp;
    Full_adder F0(ctemp[1], Sum[0], A[0], B[0], Cin);
    Full_adder F1(ctemp[2], Sum[1], A[1], B[1], ctemp[1]);
    Full_adder F2(ctemp[3], Sum[2], A[2], B[2], ctemp[2]);
    Full_adder F3(ctemp[4], Sum[3], A[3], B[3], ctemp[3]);
    Full_adder F4(ctemp[5], Sum[4], A[4], B[4], ctemp[4]);
    Full_adder F5(ctemp[6], Sum[5], A[5], B[5], ctemp[5]);
    Full_adder F6(ctemp[7], Sum[6], A[6], B[6], ctemp[6]);
    Full_adder F7(ctemp[8], Sum[7], A[7], B[7], ctemp[7]);
    Full_adder F8(ctemp[9], Sum[8], A[8], B[8], ctemp[8]);
    Full_adder F9(ctemp[10], Sum[9], A[9], B[9], ctemp[9]);
    Full_adder F10(ctemp[11], Sum[10], A[10], B[10], ctemp[10]);
    Full_adder F11(ctemp[12], Sum[11], A[11], B[11], ctemp[11]);
    Full_adder F12(ctemp[13], Sum[12], A[12], B[12], ctemp[12]);
    Full_adder F13(ctemp[14], Sum[13], A[13], B[13], ctemp[13]);
    Full_adder F14(ctemp[15], Sum[14], A[14], B[14], ctemp[14]);
    Full_adder F15(ctemp[16], Sum[15], A[15], B[15], ctemp[15]);
    Full_adder F16(ctemp[17], Sum[16], A[16], B[16], ctemp[16]);
    Full_adder F17(ctemp[18], Sum[17], A[17], B[17], ctemp[17]);
    Full_adder F18(ctemp[19], Sum[18], A[18], B[18], ctemp[18]);
    Full_adder F19(ctemp[20], Sum[19], A[19], B[19], ctemp[19]);
    Full_adder F20(ctemp[21], Sum[20], A[20], B[20], ctemp[20]);
    Full_adder F21(ctemp[22], Sum[21], A[21], B[21], ctemp[21]);
    Full_adder F22(ctemp[23], Sum[22], A[22], B[22], ctemp[22]);
    Full_adder F23(ctemp[24], Sum[23], A[23], B[23], ctemp[23]);
    Full_adder F24(ctemp[25], Sum[24], A[24], B[24], ctemp[24]);
    Full_adder F25(ctemp[26], Sum[25], A[25], B[25], ctemp[25]);
    Full_adder F26(ctemp[27], Sum[26], A[26], B[26], ctemp[26]);
    Full_adder F27(ctemp[28], Sum[27], A[27], B[27], ctemp[27]);
    Full_adder F28(ctemp[29], Sum[28], A[28], B[28], ctemp[28]);
    Full_adder F29(ctemp[30], Sum[29], A[29], B[29], ctemp[29]);
    Full_adder F30(ctemp[31], Sum[30], A[30], B[30], ctemp[30]);
    Full_adder F31(Cout,     Sum[31], A[31], B[31], ctemp[31]);
endmodule

mul.v
module mul(
    input wire[31:0] A,
    input wire[31:0] B,
    input wire clk,
    input wire rst,
    output reg[63:0] result
);
    wire [31:0]tmp, overflowtmp;
    wire Cout;
    reg [5:0]count;

Adder32 plus(
    .Cout(Cout),
    .A(A),
    .B(result[31:0]),
    .Sum(tmp),
    .Cin(1'b0)
);

Adder32 overflow(
    .A(result[63:32]),
    .B(1),
    .Sum(overflowtmp),
    .Cin(1'b0)
);
    always @(*) begin
        if(rst) begin
            result=64'b0;
            count = 31;
        end else begin
        end
    end

    always @(posedge clk) begin
        if(count < 0) begin
        end else begin
            if(B[count]) begin
                result[31:0] = tmp;
                if(Cout) begin
                    result[63:32] = overflowtmp;
                end else begin
                end
            end else begin
            end
            if(count != 0) begin
                result = result << 1;
            end
            count = count - 1;
        end
    end

endmodule

testbench.v
module testbench;
    reg [31:0] A, B;
    wire [63:0] result;
    reg clk,rst;
    reg [5:0] count;
    integer i;
    mul alu(
        .A(A),
        .B(B),
        .result(result),
        .clk(clk),
        .rst(rst)
    );
     initial begin
        $dumpfile("waveform.vcd");  
        $dumpvars(0, testbench);    
    end

    initial begin
        #10
        for ( i = 0; i < 33; i = i + 1) begin
            if(i==0)begin
                #5 clk = 0; rst =1 ; #5 clk = 1; B = 32'h00000003; A = 32'h0000000F;
            end
            else begin
                #5 clk = 0; #5 clk = 1; rst = 0;
            end  
        end
        
        // 3 * 15
        if (result == 64'h000000000000002D) begin
            $display("Test 1 Passed: %d * %d = %d", A, B, result);
        end else begin
            $display("Test 1 Failed: %d * %d != %d (result: %d )", A, B, 15 * 3, result);
        end

        for ( i = 0; i < 33; i = i + 1) begin
            if(i==0)begin
                #5 clk = 0; rst =1 ; #5 clk = 1; B = 32'h00000000; A = 32'h11111111;
            end
            else begin
                #5 clk = 0; #5 clk = 1; rst = 0 ;
            end  
        end
        //0 * 最大數 
        if (result == 64'h0000000000000000) begin
            $display("Test 2 Passed: %d * %d = %d", A, B, result);
        end else begin
            $display("Test 2 Failed: %d * %d != %d (result: %d)", A, B, 0, result);
        end

        for ( i = 0; i < 33; i = i + 1) begin
            if(i==0)begin
                #5 clk = 0; rst =1 ; #5 clk = 1; B = 32'h0000007D; A = 32'h0000004E;
            end
            else begin
                #5 clk = 0; #5 clk = 1; rst = 0 ;
            end  
        end
        //125 * 78
        if (result == 64'h0000000000002616) begin
            $display("Test 2 Passed: %d * %d = %d", A, B, result);
        end else begin
            $display("Test 2 Failed: %d * %d != %d (result: %d)", A, B, 9750, result);
        end

        $finish;
    end

   
endmodule

waveform.vcd
$date
	Sun Nov 10 23:26:26 2024
$end
$version
	Icarus Verilog
$end
$timescale
	1s
$end
$scope module testbench $end
$var wire 64 ! result [63:0] $end
$var reg 32 " A [31:0] $end
$var reg 32 # B [31:0] $end
$var reg 1 $ clk $end
$var reg 1 % rst $end
$var integer 32 & i [31:0] $end
$scope module alu $end
$var wire 32 ' A [31:0] $end
$var wire 32 ( B [31:0] $end
$var wire 1 $ clk $end
$var wire 1 % rst $end
$var wire 32 ) tmp [31:0] $end
$var wire 32 * overflowtmp [31:0] $end
$var wire 1 + Cout $end
$var reg 6 , count [5:0] $end
$var reg 64 - result [63:0] $end
$scope module overflow $end
$var wire 32 . A [31:0] $end
$var wire 32 / B [31:0] $end
$var wire 1 0 Cin $end
$var wire 31 1 ctemp [31:1] $end
$var wire 32 2 Sum [31:0] $end
$var wire 1 3 Cout $end
$scope module F0 $end
$var wire 1 4 A $end
$var wire 1 5 B $end
$var wire 1 0 Cin $end
$var wire 1 6 Cout $end
$var wire 1 7 Sum $end
$upscope $end
$scope module F1 $end
$var wire 1 8 A $end
$var wire 1 9 B $end
$var wire 1 : Cin $end
$var wire 1 ; Cout $end
$var wire 1 < Sum $end
$upscope $end
$scope module F10 $end
$var wire 1 = A $end
$var wire 1 > B $end
$var wire 1 ? Cin $end
$var wire 1 @ Cout $end
$var wire 1 A Sum $end
$upscope $end
$scope module F11 $end
$var wire 1 B A $end
$var wire 1 C B $end
$var wire 1 D Cin $end
$var wire 1 E Cout $end
$var wire 1 F Sum $end
$upscope $end
$scope module F12 $end
$var wire 1 G A $end
$var wire 1 H B $end
$var wire 1 I Cin $end
$var wire 1 J Cout $end
$var wire 1 K Sum $end
$upscope $end
$scope module F13 $end
$var wire 1 L A $end
$var wire 1 M B $end
$var wire 1 N Cin $end
$var wire 1 O Cout $end
$var wire 1 P Sum $end
$upscope $end
$scope module F14 $end
$var wire 1 Q A $end
$var wire 1 R B $end
$var wire 1 S Cin $end
$var wire 1 T Cout $end
$var wire 1 U Sum $end
$upscope $end
$scope module F15 $end
$var wire 1 V A $end
$var wire 1 W B $end
$var wire 1 X Cin $end
$var wire 1 Y Cout $end
$var wire 1 Z Sum $end
$upscope $end
$scope module F16 $end
$var wire 1 [ A $end
$var wire 1 \ B $end
$var wire 1 ] Cin $end
$var wire 1 ^ Cout $end
$var wire 1 _ Sum $end
$upscope $end
$scope module F17 $end
$var wire 1 ` A $end
$var wire 1 a B $end
$var wire 1 b Cin $end
$var wire 1 c Cout $end
$var wire 1 d Sum $end
$upscope $end
$scope module F18 $end
$var wire 1 e A $end
$var wire 1 f B $end
$var wire 1 g Cin $end
$var wire 1 h Cout $end
$var wire 1 i Sum $end
$upscope $end
$scope module F19 $end
$var wire 1 j A $end
$var wire 1 k B $end
$var wire 1 l Cin $end
$var wire 1 m Cout $end
$var wire 1 n Sum $end
$upscope $end
$scope module F2 $end
$var wire 1 o A $end
$var wire 1 p B $end
$var wire 1 q Cin $end
$var wire 1 r Cout $end
$var wire 1 s Sum $end
$upscope $end
$scope module F20 $end
$var wire 1 t A $end
$var wire 1 u B $end
$var wire 1 v Cin $end
$var wire 1 w Cout $end
$var wire 1 x Sum $end
$upscope $end
$scope module F21 $end
$var wire 1 y A $end
$var wire 1 z B $end
$var wire 1 { Cin $end
$var wire 1 | Cout $end
$var wire 1 } Sum $end
$upscope $end
$scope module F22 $end
$var wire 1 ~ A $end
$var wire 1 !" B $end
$var wire 1 "" Cin $end
$var wire 1 #" Cout $end
$var wire 1 $" Sum $end
$upscope $end
$scope module F23 $end
$var wire 1 %" A $end
$var wire 1 &" B $end
$var wire 1 '" Cin $end
$var wire 1 (" Cout $end
$var wire 1 )" Sum $end
$upscope $end
$scope module F24 $end
$var wire 1 *" A $end
$var wire 1 +" B $end
$var wire 1 ," Cin $end
$var wire 1 -" Cout $end
$var wire 1 ." Sum $end
$upscope $end
$scope module F25 $end
$var wire 1 /" A $end
$var wire 1 0" B $end
$var wire 1 1" Cin $end
$var wire 1 2" Cout $end
$var wire 1 3" Sum $end
$upscope $end
$scope module F26 $end
$var wire 1 4" A $end
$var wire 1 5" B $end
$var wire 1 6" Cin $end
$var wire 1 7" Cout $end
$var wire 1 8" Sum $end
$upscope $end
$scope module F27 $end
$var wire 1 9" A $end
$var wire 1 :" B $end
$var wire 1 ;" Cin $end
$var wire 1 <" Cout $end
$var wire 1 =" Sum $end
$upscope $end
$scope module F28 $end
$var wire 1 >" A $end
$var wire 1 ?" B $end
$var wire 1 @" Cin $end
$var wire 1 A" Cout $end
$var wire 1 B" Sum $end
$upscope $end
$scope module F29 $end
$var wire 1 C" A $end
$var wire 1 D" B $end
$var wire 1 E" Cin $end
$var wire 1 F" Cout $end
$var wire 1 G" Sum $end
$upscope $end
$scope module F3 $end
$var wire 1 H" A $end
$var wire 1 I" B $end
$var wire 1 J" Cin $end
$var wire 1 K" Cout $end
$var wire 1 L" Sum $end
$upscope $end
$scope module F30 $end
$var wire 1 M" A $end
$var wire 1 N" B $end
$var wire 1 O" Cin $end
$var wire 1 P" Cout $end
$var wire 1 Q" Sum $end
$upscope $end
$scope module F31 $end
$var wire 1 R" A $end
$var wire 1 S" B $end
$var wire 1 T" Cin $end
$var wire 1 3 Cout $end
$var wire 1 U" Sum $end
$upscope $end
$scope module F4 $end
$var wire 1 V" A $end
$var wire 1 W" B $end
$var wire 1 X" Cin $end
$var wire 1 Y" Cout $end
$var wire 1 Z" Sum $end
$upscope $end
$scope module F5 $end
$var wire 1 [" A $end
$var wire 1 \" B $end
$var wire 1 ]" Cin $end
$var wire 1 ^" Cout $end
$var wire 1 _" Sum $end
$upscope $end
$scope module F6 $end
$var wire 1 `" A $end
$var wire 1 a" B $end
$var wire 1 b" Cin $end
$var wire 1 c" Cout $end
$var wire 1 d" Sum $end
$upscope $end
$scope module F7 $end
$var wire 1 e" A $end
$var wire 1 f" B $end
$var wire 1 g" Cin $end
$var wire 1 h" Cout $end
$var wire 1 i" Sum $end
$upscope $end
$scope module F8 $end
$var wire 1 j" A $end
$var wire 1 k" B $end
$var wire 1 l" Cin $end
$var wire 1 m" Cout $end
$var wire 1 n" Sum $end
$upscope $end
$scope module F9 $end
$var wire 1 o" A $end
$var wire 1 p" B $end
$var wire 1 q" Cin $end
$var wire 1 r" Cout $end
$var wire 1 s" Sum $end
$upscope $end
$upscope $end
$scope module plus $end
$var wire 32 t" A [31:0] $end
$var wire 32 u" B [31:0] $end
$var wire 1 v" Cin $end
$var wire 31 w" ctemp [31:1] $end
$var wire 32 x" Sum [31:0] $end
$var wire 1 + Cout $end
$scope module F0 $end
$var wire 1 y" A $end
$var wire 1 z" B $end
$var wire 1 v" Cin $end
$var wire 1 {" Cout $end
$var wire 1 |" Sum $end
$upscope $end
$scope module F1 $end
$var wire 1 }" A $end
$var wire 1 ~" B $end
$var wire 1 !# Cin $end
$var wire 1 "# Cout $end
$var wire 1 ## Sum $end
$upscope $end
$scope module F10 $end
$var wire 1 $# A $end
$var wire 1 %# B $end
$var wire 1 &# Cin $end
$var wire 1 '# Cout $end
$var wire 1 (# Sum $end
$upscope $end
$scope module F11 $end
$var wire 1 )# A $end
$var wire 1 *# B $end
$var wire 1 +# Cin $end
$var wire 1 ,# Cout $end
$var wire 1 -# Sum $end
$upscope $end
$scope module F12 $end
$var wire 1 .# A $end
$var wire 1 /# B $end
$var wire 1 0# Cin $end
$var wire 1 1# Cout $end
$var wire 1 2# Sum $end
$upscope $end
$scope module F13 $end
$var wire 1 3# A $end
$var wire 1 4# B $end
$var wire 1 5# Cin $end
$var wire 1 6# Cout $end
$var wire 1 7# Sum $end
$upscope $end
$scope module F14 $end
$var wire 1 8# A $end
$var wire 1 9# B $end
$var wire 1 :# Cin $end
$var wire 1 ;# Cout $end
$var wire 1 <# Sum $end
$upscope $end
$scope module F15 $end
$var wire 1 =# A $end
$var wire 1 ># B $end
$var wire 1 ?# Cin $end
$var wire 1 @# Cout $end
$var wire 1 A# Sum $end
$upscope $end
$scope module F16 $end
$var wire 1 B# A $end
$var wire 1 C# B $end
$var wire 1 D# Cin $end
$var wire 1 E# Cout $end
$var wire 1 F# Sum $end
$upscope $end
$scope module F17 $end
$var wire 1 G# A $end
$var wire 1 H# B $end
$var wire 1 I# Cin $end
$var wire 1 J# Cout $end
$var wire 1 K# Sum $end
$upscope $end
$scope module F18 $end
$var wire 1 L# A $end
$var wire 1 M# B $end
$var wire 1 N# Cin $end
$var wire 1 O# Cout $end
$var wire 1 P# Sum $end
$upscope $end
$scope module F19 $end
$var wire 1 Q# A $end
$var wire 1 R# B $end
$var wire 1 S# Cin $end
$var wire 1 T# Cout $end
$var wire 1 U# Sum $end
$upscope $end
$scope module F2 $end
$var wire 1 V# A $end
$var wire 1 W# B $end
$var wire 1 X# Cin $end
$var wire 1 Y# Cout $end
$var wire 1 Z# Sum $end
$upscope $end
$scope module F20 $end
$var wire 1 [# A $end
$var wire 1 \# B $end
$var wire 1 ]# Cin $end
$var wire 1 ^# Cout $end
$var wire 1 _# Sum $end
$upscope $end
$scope module F21 $end
$var wire 1 `# A $end
$var wire 1 a# B $end
$var wire 1 b# Cin $end
$var wire 1 c# Cout $end
$var wire 1 d# Sum $end
$upscope $end
$scope module F22 $end
$var wire 1 e# A $end
$var wire 1 f# B $end
$var wire 1 g# Cin $end
$var wire 1 h# Cout $end
$var wire 1 i# Sum $end
$upscope $end
$scope module F23 $end
$var wire 1 j# A $end
$var wire 1 k# B $end
$var wire 1 l# Cin $end
$var wire 1 m# Cout $end
$var wire 1 n# Sum $end
$upscope $end
$scope module F24 $end
$var wire 1 o# A $end
$var wire 1 p# B $end
$var wire 1 q# Cin $end
$var wire 1 r# Cout $end
$var wire 1 s# Sum $end
$upscope $end
$scope module F25 $end
$var wire 1 t# A $end
$var wire 1 u# B $end
$var wire 1 v# Cin $end
$var wire 1 w# Cout $end
$var wire 1 x# Sum $end
$upscope $end
$scope module F26 $end
$var wire 1 y# A $end
$var wire 1 z# B $end
$var wire 1 {# Cin $end
$var wire 1 |# Cout $end
$var wire 1 }# Sum $end
$upscope $end
$scope module F27 $end
$var wire 1 ~# A $end
$var wire 1 !$ B $end
$var wire 1 "$ Cin $end
$var wire 1 #$ Cout $end
$var wire 1 $$ Sum $end
$upscope $end
$scope module F28 $end
$var wire 1 %$ A $end
$var wire 1 &$ B $end
$var wire 1 '$ Cin $end
$var wire 1 ($ Cout $end
$var wire 1 )$ Sum $end
$upscope $end
$scope module F29 $end
$var wire 1 *$ A $end
$var wire 1 +$ B $end
$var wire 1 ,$ Cin $end
$var wire 1 -$ Cout $end
$var wire 1 .$ Sum $end
$upscope $end
$scope module F3 $end
$var wire 1 /$ A $end
$var wire 1 0$ B $end
$var wire 1 1$ Cin $end
$var wire 1 2$ Cout $end
$var wire 1 3$ Sum $end
$upscope $end
$scope module F30 $end
$var wire 1 4$ A $end
$var wire 1 5$ B $end
$var wire 1 6$ Cin $end
$var wire 1 7$ Cout $end
$var wire 1 8$ Sum $end
$upscope $end
$scope module F31 $end
$var wire 1 9$ A $end
$var wire 1 :$ B $end
$var wire 1 ;$ Cin $end
$var wire 1 + Cout $end
$var wire 1 <$ Sum $end
$upscope $end
$scope module F4 $end
$var wire 1 =$ A $end
$var wire 1 >$ B $end
$var wire 1 ?$ Cin $end
$var wire 1 @$ Cout $end
$var wire 1 A$ Sum $end
$upscope $end
$scope module F5 $end
$var wire 1 B$ A $end
$var wire 1 C$ B $end
$var wire 1 D$ Cin $end
$var wire 1 E$ Cout $end
$var wire 1 F$ Sum $end
$upscope $end
$scope module F6 $end
$var wire 1 G$ A $end
$var wire 1 H$ B $end
$var wire 1 I$ Cin $end
$var wire 1 J$ Cout $end
$var wire 1 K$ Sum $end
$upscope $end
$scope module F7 $end
$var wire 1 L$ A $end
$var wire 1 M$ B $end
$var wire 1 N$ Cin $end
$var wire 1 O$ Cout $end
$var wire 1 P$ Sum $end
$upscope $end
$scope module F8 $end
$var wire 1 Q$ A $end
$var wire 1 R$ B $end
$var wire 1 S$ Cin $end
$var wire 1 T$ Cout $end
$var wire 1 U$ Sum $end
$upscope $end
$scope module F9 $end
$var wire 1 V$ A $end
$var wire 1 W$ B $end
$var wire 1 X$ Cin $end
$var wire 1 Y$ Cout $end
$var wire 1 Z$ Sum $end
$upscope $end
$upscope $end
$upscope $end
$upscope $end
$enddefinitions $end
#0
$dumpvars
xZ$
xY$
xX$
xW$
xV$
xU$
xT$
xS$
xR$
xQ$
xP$
xO$
xN$
xM$
xL$
xK$
xJ$
xI$
xH$
xG$
xF$
xE$
xD$
xC$
xB$
xA$
x@$
x?$
x>$
x=$
x<$
x;$
x:$
x9$
x8$
x7$
x6$
x5$
x4$
x3$
x2$
x1$
x0$
x/$
x.$
x-$
x,$
x+$
x*$
x)$
x($
x'$
x&$
x%$
x$$
x#$
x"$
x!$
x~#
x}#
x|#
x{#
xz#
xy#
xx#
xw#
xv#
xu#
xt#
xs#
xr#
xq#
xp#
xo#
xn#
xm#
xl#
xk#
xj#
xi#
xh#
xg#
xf#
xe#
xd#
xc#
xb#
xa#
x`#
x_#
x^#
x]#
x\#
x[#
xZ#
xY#
xX#
xW#
xV#
xU#
xT#
xS#
xR#
xQ#
xP#
xO#
xN#
xM#
xL#
xK#
xJ#
xI#
xH#
xG#
xF#
xE#
xD#
xC#
xB#
xA#
x@#
x?#
x>#
x=#
x<#
x;#
x:#
x9#
x8#
x7#
x6#
x5#
x4#
x3#
x2#
x1#
x0#
x/#
x.#
x-#
x,#
x+#
x*#
x)#
x(#
x'#
x&#
x%#
x$#
x##
x"#
x!#
x~"
x}"
x|"
x{"
xz"
xy"
bx x"
bx w"
0v"
bx u"
bx t"
xs"
xr"
xq"
0p"
xo"
xn"
xm"
xl"
0k"
xj"
xi"
xh"
xg"
0f"
xe"
xd"
xc"
xb"
0a"
x`"
x_"
x^"
x]"
0\"
x["
xZ"
xY"
xX"
0W"
xV"
xU"
xT"
0S"
xR"
xQ"
xP"
xO"
0N"
xM"
xL"
xK"
xJ"
0I"
xH"
xG"
xF"
xE"
0D"
xC"
xB"
xA"
x@"
0?"
x>"
x="
x<"
x;"
0:"
x9"
x8"
x7"
x6"
05"
x4"
x3"
x2"
x1"
00"
x/"
x."
x-"
x,"
0+"
x*"
x)"
x("
x'"
0&"
x%"
x$"
x#"
x""
0!"
x~
x}
x|
x{
0z
xy
xx
xw
xv
0u
xt
xs
xr
xq
0p
xo
xn
xm
xl
0k
xj
xi
xh
xg
0f
xe
xd
xc
xb
0a
x`
x_
x^
x]
0\
x[
xZ
xY
xX
0W
xV
xU
xT
xS
0R
xQ
xP
xO
xN
0M
xL
xK
xJ
xI
0H
xG
xF
xE
xD
0C
xB
xA
x@
x?
0>
x=
x<
x;
x:
09
x8
x7
x6
15
x4
x3
bx 2
bx 1
00
b1 /
bx .
bx -
bx ,
x+
bx *
bx )
bx (
bx '
bx &
x%
x$
bx #
bx "
bx !
$end
#10
b0 &
#15
0+
0;$
07$
06$
0-$
0,$
0($
0'$
0#$
0"$
0|#
0{#
0w#
0v#
0r#
0q#
0m#
0l#
0h#
0g#
0c#
0b#
0^#
0]#
0T#
0S#
0O#
0N#
0J#
0I#
0E#
0D#
0@#
0?#
0;#
0:#
06#
05#
01#
00#
0,#
0+#
0'#
0&#
0Y$
0X$
0T$
0S$
0O$
0N$
0J$
0I$
0E$
0D$
0@$
0?$
02$
01$
0Y#
0X#
0"#
0<
0!#
0:
0s
0L"
0Z"
0_"
0d"
0i"
0n"
0s"
0A
0F
0K
0P
0U
0Z
0_
0d
0i
0n
0x
0}
0$"
0)"
0."
03"
08"
0="
0B"
0G"
0Q"
0U"
b0 w"
0{"
06
0q
0J"
0X"
0]"
0b"
0g"
0l"
0q"
0?
0D
0I
0N
0S
0X
0]
0b
0g
0l
0v
0{
0""
0'"
0,"
01"
06"
0;"
0@"
0E"
0O"
0T"
b1 *
b1 2
17
0;
0r
0K"
0Y"
0^"
0c"
0h"
0m"
0r"
0@
0E
0J
0O
0T
0Y
0^
0c
0h
0m
0w
0|
0#"
0("
0-"
02"
07"
0<"
0A"
0F"
b0 1
0P"
03
0z"
0~"
0W#
00$
0>$
0C$
0H$
0M$
0R$
0W$
0%#
0*#
0/#
04#
09#
0>#
0C#
0H#
0M#
0R#
0\#
0a#
0f#
0k#
0p#
0u#
0z#
0!$
0&$
0+$
05$
0:$
04
08
0o
0H"
0V"
0["
0`"
0e"
0j"
0o"
0=
0B
0G
0L
0Q
0V
0[
0`
0e
0j
0t
0y
0~
0%"
0*"
0/"
04"
09"
0>"
0C"
0M"
0R"
b0 u"
b0 .
b11111 ,
b0 !
b0 -
1%
0$
#20
1|"
1##
1Z#
13$
0A$
0F$
0K$
0P$
0U$
0Z$
0(#
0-#
02#
07#
0<#
0A#
0F#
0K#
0P#
0U#
0_#
0d#
0i#
0n#
0s#
0x#
0}#
0$$
0)$
0.$
08$
b1111 )
b1111 x"
0<$
1y"
1}"
1V#
1/$
0=$
0B$
0G$
0L$
0Q$
0V$
0$#
0)#
0.#
03#
08#
0=#
0B#
0G#
0L#
0Q#
0[#
0`#
0e#
0j#
0o#
0t#
0y#
0~#
0%$
0*$
04$
09$
b11110 ,
b1 &
b1111 "
b1111 '
b1111 t"
b11 #
b11 (
1$
#25
0$
#30
b11101 ,
b10 &
0%
1$
#35
0$
#40
b11100 ,
b11 &
1$
#45
0$
#50
b11011 ,
b100 &
1$
#55
0$
#60
b11010 ,
b101 &
1$
#65
0$
#70
b11001 ,
b110 &
1$
#75
0$
#80
b11000 ,
b111 &
1$
#85
0$
#90
b10111 ,
b1000 &
1$
#95
0$
#100
b10110 ,
b1001 &
1$
#105
0$
#110
b10101 ,
b1010 &
1$
#115
0$
#120
b10100 ,
b1011 &
1$
#125
0$
#130
b10011 ,
b1100 &
1$
#135
0$
#140
b10010 ,
b1101 &
1$
#145
0$
#150
b10001 ,
b1110 &
1$
#155
0$
#160
b10000 ,
b1111 &
1$
#165
0$
#170
b1111 ,
b10000 &
1$
#175
0$
#180
b1110 ,
b10001 &
1$
#185
0$
#190
b1101 ,
b10010 &
1$
#195
0$
#200
b1100 ,
b10011 &
1$
#205
0$
#210
b1011 ,
b10100 &
1$
#215
0$
#220
b1010 ,
b10101 &
1$
#225
0$
#230
b1001 ,
b10110 &
1$
#235
0$
#240
b1000 ,
b10111 &
1$
#245
0$
#250
b111 ,
b11000 &
1$
#255
0$
#260
b110 ,
b11001 &
1$
#265
0$
#270
b101 ,
b11010 &
1$
#275
0$
#280
b100 ,
b11011 &
1$
#285
0$
#290
b11 ,
b11100 &
1$
#295
0$
#300
b10 ,
b11101 &
1$
#305
0$
#310
b1 ,
b11110 &
1$
#315
0$
#320
1F$
1D$
1@$
1X#
11$
1?$
1"#
1Y#
b11110 w"
12$
0##
1Z#
13$
b101101 )
b101101 x"
0A$
1~"
1W#
10$
1>$
b11110 u"
b0 ,
b11110 !
b11110 -
b11111 &
1$
#325
0$
#330
1Z#
0K$
1!#
1X#
0D$
0I$
1{"
1"#
0@$
b1111 w"
0E$
0|"
0##
1A$
b111100 )
b111100 x"
1F$
1z"
0~"
0>$
1C$
b101101 u"
b111111 ,
b101101 !
b101101 -
b100000 &
1$
#335
0$
#340
0!#
1D$
0{"
b11110 w"
1@$
1|"
0##
0Z#
0A$
1F$
b1101001 )
b1101001 x"
1K$
0z"
1~"
0W#
1>$
0C$
1H$
b1011010 u"
b111110 ,
b1011010 !
b1011010 -
b0 &
1$
#345
0?$
02$
01$
0Y#
1Z#
0F$
0X#
0D$
0"#
b0 w"
0@$
1##
13$
0A$
b1111 )
b1111 x"
0K$
0~"
00$
0>$
0H$
b0 u"
b11111 ,
b0 !
b0 -
1%
0$
#350
0##
0Z#
03$
1A$
1U$
12#
1F#
1_#
1s#
b10001000100010001000100010001 )
b10001000100010001000100010001 x"
1)$
0}"
0V#
0/$
1=$
1Q$
1.#
1B#
1[#
1o#
1%$
b11110 ,
b1 &
b10001000100010001000100010001 "
b10001000100010001000100010001 '
b10001000100010001000100010001 t"
b0 #
b0 (
1$
#355
0$
#360
b11101 ,
b10 &
0%
1$
#365
0$
#370
b11100 ,
b11 &
1$
#375
0$
#380
b11011 ,
b100 &
1$
#385
0$
#390
b11010 ,
b101 &
1$
#395
0$
#400
b11001 ,
b110 &
1$
#405
0$
#410
b11000 ,
b111 &
1$
#415
0$
#420
b10111 ,
b1000 &
1$
#425
0$
#430
b10110 ,
b1001 &
1$
#435
0$
#440
b10101 ,
b1010 &
1$
#445
0$
#450
b10100 ,
b1011 &
1$
#455
0$
#460
b10011 ,
b1100 &
1$
#465
0$
#470
b10010 ,
b1101 &
1$
#475
0$
#480
b10001 ,
b1110 &
1$
#485
0$
#490
b10000 ,
b1111 &
1$
#495
0$
#500
b1111 ,
b10000 &
1$
#505
0$
#510
b1110 ,
b10001 &
1$
#515
0$
#520
b1101 ,
b10010 &
1$
#525
0$
#530
b1100 ,
b10011 &
1$
#535
0$
#540
b1011 ,
b10100 &
1$
#545
0$
#550
b1010 ,
b10101 &
1$
#555
0$
#560
b1001 ,
b10110 &
1$
#565
0$
#570
b1000 ,
b10111 &
1$
#575
0$
#580
b111 ,
b11000 &
1$
#585
0$
#590
b110 ,
b11001 &
1$
#595
0$
#600
b101 ,
b11010 &
1$
#605
0$
#610
b100 ,
b11011 &
1$
#615
0$
#620
b11 ,
b11100 &
1$
#625
0$
#630
b10 ,
b11101 &
1$
#635
0$
#640
b1 ,
b11110 &
1$
#645
0$
#650
b0 ,
b11111 &
1$
#655
0$
#660
b111111 ,
b100000 &
1$
#665
0$
#670
b111110 ,
b0 &
1$
#675
b11111 ,
1%
0$
#680
0|"
1##
1Z#
13$
0A$
1K$
0U$
02#
0F#
0_#
0s#
b1001110 )
b1001110 x"
0)$
0y"
1}"
1V#
1/$
0=$
1G$
0Q$
0.#
0B#
0[#
0o#
0%$
b11110 ,
b1 &
b1001110 "
b1001110 '
b1001110 t"
b1111101 #
b1111101 (
1$
#685
0$
#690
b11101 ,
b10 &
0%
1$
#695
0$
#700
b11100 ,
b11 &
1$
#705
0$
#710
b11011 ,
b100 &
1$
#715
0$
#720
b11010 ,
b101 &
1$
#725
0$
#730
b11001 ,
b110 &
1$
#735
0$
#740
b11000 ,
b111 &
1$
#745
0$
#750
b10111 ,
b1000 &
1$
#755
0$
#760
b10110 ,
b1001 &
1$
#765
0$
#770
b10101 ,
b1010 &
1$
#775
0$
#780
b10100 ,
b1011 &
1$
#785
0$
#790
b10011 ,
b1100 &
1$
#795
0$
#800
b10010 ,
b1101 &
1$
#805
0$
#810
b10001 ,
b1110 &
1$
#815
0$
#820
b10000 ,
b1111 &
1$
#825
0$
#830
b1111 ,
b10000 &
1$
#835
0$
#840
b1110 ,
b10001 &
1$
#845
0$
#850
b1101 ,
b10010 &
1$
#855
0$
#860
b1100 ,
b10011 &
1$
#865
0$
#870
b1011 ,
b10100 &
1$
#875
0$
#880
b1010 ,
b10101 &
1$
#885
0$
#890
b1001 ,
b10110 &
1$
#895
0$
#900
b1000 ,
b10111 &
1$
#905
0$
#910
b111 ,
b11000 &
1$
#915
0$
#920
b110 ,
b11001 &
1$
#925
0$
#930
1F$
1D$
1@$
11$
1?$
1Y#
b11100 w"
12$
0Z#
13$
0A$
b11101010 )
b11101010 x"
1P$
1W#
10$
1>$
1M$
b10011100 u"
b101 ,
b10011100 !
b10011100 -
b11010 &
1$
#935
0$
#940
1Z$
1X$
1T$
1S$
1O$
0P$
1N$
b111011100 w"
1J$
03$
0K$
b1000100010 )
b1000100010 x"
0U$
00$
1H$
1R$
b111010100 u"
b100 ,
b111010100 !
b111010100 -
b11011 &
1$
#945
0$
#950
0F$
0Z$
0D$
0S$
0X$
0@$
0O$
b1001100 w"
0T$
1A$
1P$
0U$
b10010010010 )
b10010010010 x"
1(#
0>$
0M$
0R$
1%#
b10001000100 u"
b11 ,
b10001000100 !
b10001000100 -
b11100 &
1$
#955
0$
#960
0P$
0N$
b1100 w"
0J$
1F$
1K$
1U$
0(#
b100101110010 )
b100101110010 x"
1-#
1C$
0H$
1R$
0%#
1*#
b100100100100 u"
b10 ,
b100100100100 !
b100100100100 -
b11101 &
1$
#965
0$
